pyetw/__init__.py
pyetw/pyetw.py
pyetw-1.1.0.dist-info/LICENSE
pyetw-1.1.0.dist-info/METADATA
pyetw-1.1.0.dist-info/WHEEL
pyetw-1.1.0.dist-info/top_level.txt
pyetw-1.1.0.dist-info/RECORD
