Metadata-Version: 2.1
Name: pyetw
Version: 1.1.0
Summary: Python logging via Event Tracing for Windows
Author-email: Marius Greuel <greuelm@mgtek.com>
Project-URL: Homepage, https://github.com/mgtek/pyetw
Project-URL: Bug Tracker, https://github.com/mgtek/pyetw/issues
Keywords: etw,windows,tracelogging,traceview,traceview plus
Classifier: Programming Language :: Python :: 3
Classifier: License :: OSI Approved :: MIT License
Classifier: Operating System :: Microsoft :: Windows
Requires-Python: >=3.6
License-File: LICENSE
